dynd/cuda.pyd
dynd/_pydynd.pyd
dynd/__init__.py
dynd/nd/array_functions.py
dynd/nd/computed_fields.py
dynd/nd/elwise_gfuncs.py
dynd/nd/elwise_kernels.py
dynd/nd/elwise_reduce_gfuncs.py
dynd/nd/functional.py
dynd/nd/gfunc.py
dynd/nd/vm.py
dynd/nd/__init__.py
dynd/ndt/dim_helpers.py
dynd/ndt/dynd_ctypes.py
dynd/ndt/__init__.py
dynd/tests/test_array_as_py.py
dynd/tests/test_array_basics.py
dynd/tests/test_array_cast.py
dynd/tests/test_array_construct.py
dynd/tests/test_array_copy.py
dynd/tests/test_array_getitem.py
dynd/tests/test_array_in.py
dynd/tests/test_array_setitem.py
dynd/tests/test_array_squeeze.py
dynd/tests/test_arrfunc.py
dynd/tests/test_blaze_interop.py
dynd/tests/test_ckernel.py
dynd/tests/test_computed_fields.py
dynd/tests/test_ctypes_interop.py
dynd/tests/test_datetime.py
dynd/tests/test_dim_helpers.py
dynd/tests/test_dtype.py
dynd/tests/test_dtype_datashape.py
dynd/tests/test_elwise_map.py
dynd/tests/test_eval_context.py
dynd/tests/test_int128.py
dynd/tests/test_lowlevel.py
dynd/tests/test_nd_fields.py
dynd/tests/test_nd_groupby.py
dynd/tests/test_numpy_compat.py
dynd/tests/test_numpy_interop.py
dynd/tests/test_pickle.py
dynd/tests/test_python_list.py
dynd/tests/test_python_scalar.py
dynd/tests/test_range_linspace.py
dynd/tests/test_types_categorical.py
dynd/tests/test_type_pattern_match.py
dynd/tests/test_unicode.py
dynd/tests/__init__.py
dynd/_lowlevel/api.py
dynd/_lowlevel/arrmeta_struct.py
dynd/_lowlevel/ckernel.py
dynd/_lowlevel/ctypes_types.py
dynd/_lowlevel/kind.py
dynd/_lowlevel/type_id.py
dynd/_lowlevel/util.py
dynd/_lowlevel/__init__.py
dynd-0.6.7.dev161.dist-info/DESCRIPTION.rst
dynd-0.6.7.dev161.dist-info/METADATA
dynd-0.6.7.dev161.dist-info/metadata.json
dynd-0.6.7.dev161.dist-info/RECORD
dynd-0.6.7.dev161.dist-info/top_level.txt
dynd-0.6.7.dev161.dist-info/WHEEL
