Metadata-Version: 2.0
Name: dynd
Version: 0.6.7.dev161
Summary: Python exposure of DyND
Home-page: https://github.com/libdynd/dynd-python
Author: DyND Developers
Author-email: libdynd-dev@googlegroups.com
License: BSD
Platform: UNKNOWN
Classifier: Development Status :: 3 - Alpha
Classifier: Intended Audience :: Developers
Classifier: License :: OSI Approved :: BSD License
Requires-Dist: numpy
Requires-Dist: cython
